CHANGES.txt
bootstrap.py
buildout.cfg
setup.py
src/keas/__init__.py
src/keas.unit.egg-info/PKG-INFO
src/keas.unit.egg-info/SOURCES.txt
src/keas.unit.egg-info/dependency_links.txt
src/keas.unit.egg-info/namespace_packages.txt
src/keas.unit.egg-info/not-zip-safe
src/keas.unit.egg-info/requires.txt
src/keas.unit.egg-info/top_level.txt
src/keas/unit/README.txt
src/keas/unit/__init__.py
src/keas/unit/interfaces.py
src/keas/unit/test-conversions.dat
src/keas/unit/tests.py
src/keas/unit/unit.py